pkelib/__init__.py
pkelib/pkelib.py
pkelib-1.0.0.dist-info/LICENSE
pkelib-1.0.0.dist-info/METADATA
pkelib-1.0.0.dist-info/WHEEL
pkelib-1.0.0.dist-info/top_level.txt
pkelib-1.0.0.dist-info/RECORD
