Metadata-Version: 2.1
Name: pkelib
Version: 1.0.0
Summary: PKE library
Home-page: https://github.com/Madff386/pkelib
Author: Mdaff169
Author-email: dehersbach@gmail.com
License: UNKNOWN
Platform: UNKNOWN
Classifier: Programming Language :: Python :: 3
Classifier: License :: OSI Approved :: MIT License
Classifier: Operating System :: OS Independent
Requires-Python: >=3.7
